nk/__init__.py
nk/kbo_npb/__init__.py
nk/kbo_npb/api.py
nk/kbo_npb/data/kbo_batting.csv
nk/kbo_npb/data/kbo_debut.csv
nk/kbo_npb/data/kbo_fielding.csv
nk/kbo_npb/data/kbo_people.csv
nk/kbo_npb/data/kbo_pitching.csv
nk/kbo_npb/data/npb_batting.csv
nk/kbo_npb/data/npb_fielding.csv
nk/kbo_npb/data/npb_people.csv
nk/kbo_npb/data/npb_pitching.csv
nk/kbo_npb_mlb/__init__.py
nk/kbo_npb_mlb/api.py
nk/kbo_npb_mlb/data/kbo_batting.csv
nk/kbo_npb_mlb/data/kbo_fielding.csv
nk/kbo_npb_mlb/data/kbo_people.csv
nk/kbo_npb_mlb/data/kbo_pitching.csv
nk/kbo_npb_mlb/data/mlb_batting.csv
nk/kbo_npb_mlb/data/mlb_fielding.csv
nk/kbo_npb_mlb/data/mlb_people.csv
nk/kbo_npb_mlb/data/mlb_pitching.csv
nk/kbo_npb_mlb/data/npb_batting.csv
nk/kbo_npb_mlb/data/npb_fielding.csv
nk/kbo_npb_mlb/data/npb_people.csv
nk/kbo_npb_mlb/data/npb_pitching.csv
nk/nk_merged/__init__.py
nk/nk_merged/api.py
nk/nk_merged/data/merged_player_records.csv
nk/nk_merged/data/nk_batting.csv
nk/nk_merged/data/nk_fielding.csv
nk/nk_merged/data/nk_league.csv
nk/nk_merged/data/nk_people.csv
nk/nk_merged/data/nk_pitching.csv
nk/nk_merged/data/nk_team.csv
nk/nk_merged_tall/__init__.py
nk/nk_merged_tall/api.py
nk/nk_merged_tall/data/nk_league.csv
nk/nk_merged_tall/data/nk_playerstats_CL.csv
nk/nk_merged_tall/data/nk_playerstats_JBL.csv
nk/nk_merged_tall/data/nk_playerstats_KBO.csv
nk/nk_merged_tall/data/nk_playerstats_PL.csv
nk/nk_merged_tall/data/nk_stats.csv
nk/nk_merged_tall/data/nk_team.csv
nk_datasets-0.1.0.dist-info/METADATA
nk_datasets-0.1.0.dist-info/WHEEL
nk_datasets-0.1.0.dist-info/top_level.txt
nk_datasets-0.1.0.dist-info/RECORD
