Metadata-Version: 2.4
Name: nk_datasets
Version: 0.1.0
Summary: Standardized NK (NPB & KBO) baseball datasets with pandas loaders. Includes MLB players who appeared in NPB/KBO.
Author: Myungkeun Park
License: MIT
Requires-Python: >=3.9
Requires-Dist: pandas>=1.5
